.VERSION
AUTHORS.rst
CONTRIBUTING.rst
HISTORY.rst
LICENSE
MANIFEST.in
Pipfile
Pipfile.lock
README.rst
USAGE.rst
dev-requirements.txt
requirements.txt
setup.cfg
setup.py
docs/Makefile
docs/authors.rst
docs/conf.py
docs/contributing.rst
docs/history.rst
docs/index.rst
docs/installation.rst
docs/readme.rst
docs/usage.rst
dummyclicli/.VERSION
dummyclicli/AUTHORS.rst
dummyclicli/CONTRIBUTING.rst
dummyclicli/HISTORY.rst
dummyclicli/LICENSE
dummyclicli/Pipfile
dummyclicli/Pipfile.lock
dummyclicli/README.rst
dummyclicli/USAGE.rst
dummyclicli/__init__.py
dummyclicli/_version.py
dummyclicli/dev-requirements.txt
dummyclicli/dummy-clicliexceptions.py
dummyclicli/dummyclicli.py
dummyclicli/requirements.txt
dummyclicli.egg-info/PKG-INFO
dummyclicli.egg-info/SOURCES.txt
dummyclicli.egg-info/dependency_links.txt
dummyclicli.egg-info/entry_points.txt
dummyclicli.egg-info/not-zip-safe
dummyclicli.egg-info/requires.txt
dummyclicli.egg-info/top_level.txt
dummyclicli/conf/logging.json-example