Metadata-Version: 2.1
Name: dummyclicli
Version: 0.1.0
Summary: dummy cli
Home-page: https://github.com/jvilders/Dummy-cli.git
Author: Jona Vilders
Author-email: jonavilders@gmail.com
License: MIT
Keywords: dummyclicli cli
Platform: UNKNOWN
Classifier: Development Status :: 1 - Planning
Classifier: Intended Audience :: Developers
Classifier: License :: OSI Approved :: MIT License
Classifier: Natural Language :: English
Classifier: Programming Language :: Python :: 3.7
License-File: LICENSE
License-File: AUTHORS.rst
